ship_env/__init__.py
ship_env/envs/__init__.py
ship_env/envs/env_ship.py
ship_env-0.0.1.dist-info/METADATA
ship_env-0.0.1.dist-info/WHEEL
ship_env-0.0.1.dist-info/top_level.txt
ship_env-0.0.1.dist-info/RECORD
