Metadata-Version: 2.1
Name: ship-env
Version: 0.0.1
Summary: A OpenAI Gym Env for ship
Requires-Dist: gym
